Workbook

Sheet ERP Control
A1: LTM | INTERCOMPANY CONTROL COCKPIT | ERP Document Display
A3: Source file | B3: FBL5N_AR_Data_vs_FBL1N_AP.xlsx
A4: Invoice count | B4: 10
A5: System ID | B5: LTM-ERP-PRD
A6: Document type | B6: DR - Customer Invoice
A7: Output type | B7: ZIC_INV
A8: Bank name | B8: DBS Global
A9: Sample account number | B9: 000-123456-789
A10: Sample SWIFT / BIC | B10: DBSXSG00XXX
A11: Seller entity | B11: LTM Services UK Limited
A12: Buyer entity | B12: LTM Solutions Europe GmbH
A13: Control logic | B13: AP source amount + generated AR amount = zero in local and document currency
A14: Disclaimer | B14: SAP-style illustrative output; not generated by SAP. Sample bank identifiers and statutory fields require replacement with approved master data.

Sheet Invoice Register
A1: LTM | 10 INVOICE REGISTER | ERP Document Display
A3: LTM Invoice No. | B3: SAP AR Document | C3: Source AP Document | D3: Document Type | E3: Document Date | F3: Due Date | G3: Customer Account | H3: Vendor Account | I3: Seller Entity | J3: Buyer Entity | K3: Reference | L3: Trading Partner | M3: Document Currency | N3: AR Doc Amount | O3: AP Doc Amount | P3: Local Currency | Q3: AR Local Amount | R3: AP Local Amount | S3: Bank Name | T3: Payment Status | U3: Original Match Status | V3: Mirror Control | W3: Comments
A4: LTM-IC-2026-0001 | B4: 1800000003 | C4: 1900000002 | D4: DR | E4: 46202 | F4: 46262 | G4: 20004 | H4: 10004 | I4: LTM Services UK Limited | J4: LTM Solutions Europe GmbH | K4: WBS TEST -LAB | L4: EU_200 | M4: EUR | N4: 39000 | O4: -39000 | P4: GBP | Q4: 34054.8 | R4: -34054.8 | S4: DBS Global | T4: Open | U4: Not Matched | V4: =IF(AND(ABS(N4+O4)<=0.01,ABS(Q4+R4)<=0.01),"Matched","Exception") -> Matched | W4: Generated from FBL5N reference
A5: LTM-IC-2026-0002 | B5: 1800000004 | C5: 1900000003 | D5: DR | E5: 46202 | F5: 46262 | G5: 20004 | H5: 10004 | I5: LTM Services UK Limited | J5: LTM Solutions Europe GmbH | K5: LAB - NO WBS | L5: EU_200 | M5: EUR | N5: 39000 | O5: -39000 | P5: GBP | Q5: 34054.8 | R5: -34054.8 | S5: DBS Global | T5: Open | U5: Not Matched | V5: =IF(AND(ABS(N5+O5)<=0.01,ABS(Q5+R5)<=0.01),"Matched","Exception") -> Matched | W5: Generated from FBL5N reference
A6: LTM-IC-2026-0003 | B6: 1800000005 | C6: 1900000660 | D6: DR | E6: 45624 | F6: 45684 | G6: 20004 | H6: 10004 | I6: LTM Services UK Limited | J6: LTM Solutions Europe GmbH | K6: 90050558 | L6: EU_200 | M6: EUR | N6: 68739.02 | O6: -68739.02 | P6: GBP | Q6: 58572.52 | R6: -58572.52 | S6: DBS Global | T6: Open | U6: Not Matched | V6: =IF(AND(ABS(N6+O6)<=0.01,ABS(Q6+R6)<=0.01),"Matched","Exception") -> Matched | W6: Generated from FBL5N reference
A7: LTM-IC-2026-0004 | B7: 1800000006 | C7: 1900000661 | D7: DR | E7: 45624 | F7: 45684 | G7: 20004 | H7: 10004 | I7: LTM Services UK Limited | J7: LTM Solutions Europe GmbH | K7: 90050559 | L7: EU_200 | M7: EUR | N7: 37176.16 | O7: -37176.16 | P7: GBP | Q7: 31677.81 | R7: -31677.81 | S7: DBS Global | T7: Open | U7: Not Matched | V7: =IF(AND(ABS(N7+O7)<=0.01,ABS(Q7+R7)<=0.01),"Matched","Exception") -> Matched | W7: Generated from FBL5N reference
A8: LTM-IC-2026-0005 | B8: 1800000007 | C8: 1900000662 | D8: DR | E8: 45624 | F8: 45684 | G8: 20004 | H8: 10004 | I8: LTM Services UK Limited | J8: LTM Solutions Europe GmbH | K8: 90050561 | L8: EU_200 | M8: EUR | N8: 44879.86 | O8: -44879.86 | P8: GBP | Q8: 38242.13 | R8: -38242.13 | S8: DBS Global | T8: Open | U8: Not Matched | V8: =IF(AND(ABS(N8+O8)<=0.01,ABS(Q8+R8)<=0.01),"Matched","Exception") -> Matched | W8: Generated from FBL5N reference
A9: LTM-IC-2026-0006 | B9: 1800000008 | C9: 1900000663 | D9: DR | E9: 45632 | F9: 45692 | G9: 20004 | H9: 10004 | I9: LTM Services UK Limited | J9: LTM Solutions Europe GmbH | K9: 0F00000383 | L9: EU_200 | M9: EUR | N9: 73192.67 | O9: -73192.67 | P9: GBP | Q9: 62367.47 | R9: -62367.47 | S9: DBS Global | T9: Open | U9: Not Matched | V9: =IF(AND(ABS(N9+O9)<=0.01,ABS(Q9+R9)<=0.01),"Matched","Exception") -> Matched | W9: Generated from FBL5N reference
A10: LTM-IC-2026-0007 | B10: 1800000009 | C10: 1900000664 | D10: DR | E10: 45632 | F10: 45692 | G10: 20004 | H10: 10004 | I10: LTM Services UK Limited | J10: LTM Solutions Europe GmbH | K10: 0F00000400 | L10: EU_200 | M10: EUR | N10: 118273.38 | O10: -118273.38 | P10: GBP | Q10: 100780.75 | R10: -100780.75 | S10: DBS Global | T10: Open | U10: Not Matched | V10: =IF(AND(ABS(N10+O10)<=0.01,ABS(Q10+R10)<=0.01),"Matched","Exception") -> Matched | W10: Generated from FBL5N reference
A11: LTM-IC-2026-0008 | B11: 1800000010 | C11: 1900000665 | D11: DR | E11: 45632 | F11: 45692 | G11: 20004 | H11: 10004 | I11: LTM Services UK Limited | J11: LTM Solutions Europe GmbH | K11: 0F00000406 | L11: EU_200 | M11: EUR | N11: 43374.03 | O11: -43374.03 | P11: GBP | Q11: 36959.01 | R11: -36959.01 | S11: DBS Global | T11: Open | U11: Not Matched | V11: =IF(AND(ABS(N11+O11)<=0.01,ABS(Q11+R11)<=0.01),"Matched","Exception") -> Matched | W11: Generated from FBL5N reference
A12: LTM-IC-2026-0009 | B12: 1800000011 | C12: 1900000666 | D12: DR | E12: 45635 | F12: 45695 | G12: 20004 | H12: 10004 | I12: LTM Services UK Limited | J12: LTM Solutions Europe GmbH | K12: 0F00000466 | L12: EU_200 | M12: EUR | N12: 184379.74 | O12: -184379.74 | P12: GBP | Q12: 157109.98 | R12: -157109.98 | S12: DBS Global | T12: Open | U12: Not Matched | V12: =IF(AND(ABS(N12+O12)<=0.01,ABS(Q12+R12)<=0.01),"Matched","Exception") -> Matched | W12: Generated from FBL5N reference
A13: LTM-IC-2026-0010 | B13: 1800000012 | C13: 1900000667 | D13: DR | E13: 45635 | F13: 45695 | G13: 20004 | H13: 10004 | I13: LTM Services UK Limited | J13: LTM Solutions Europe GmbH | K13: 0F00000472 | L13: EU_200 | M13: EUR | N13: 11923.77 | O13: -11923.77 | P13: GBP | Q13: 10160.24 | R13: -10160.24 | S13: DBS Global | T13: Open | U13: Not Matched | V13: =IF(AND(ABS(N13+O13)<=0.01,ABS(Q13+R13)<=0.01),"Matched","Exception") -> Matched | W13: Generated from FBL5N reference

Sheet FBL5N AR Extract
A1: LTM | FBL5N AR SELECTED ITEMS | ERP Document Display
A3: SAP AR Document | B3: Customer Account | C3: Document Type | D3: Document Date | E3: Due Date | F3: Reference | G3: Trading Partner | H3: Document Currency | I3: AR Doc Amount | J3: Local Currency | K3: AR Local Amount | L3: Source AP Document | M3: Source Vendor | N3: Match Status | O3: Matched With | P3: Invoice No.
A4: 1800000003 | B4: 20004 | C4: DR | D4: 46202 | E4: 46262 | F4: WBS TEST -LAB | G4: EU_200 | H4: EUR | I4: 39000 | J4: GBP | K4: 34054.8 | L4: 1900000002 | M4: 10004 | N4: Not Matched | O4: Invoice number booked differently | P4: WBS TEST -LAB
A5: 1800000004 | B5: 20004 | C5: DR | D5: 46202 | E5: 46262 | F5: LAB - NO WBS | G5: EU_200 | H5: EUR | I5: 39000 | J5: GBP | K5: 34054.8 | L5: 1900000003 | M5: 10004 | N5: Not Matched | O5: Invoice number booked differently | P5: LAB - NO WBS
A6: 1800000005 | B6: 20004 | C6: DR | D6: 45624 | E6: 45684 | F6: 90050558 | G6: EU_200 | H6: EUR | I6: 68739.02 | J6: GBP | K6: 58572.52 | L6: 1900000660 | M6: 10004 | N6: Not Matched | P6: 90050558
A7: 1800000006 | B7: 20004 | C7: DR | D7: 45624 | E7: 45684 | F7: 90050559 | G7: EU_200 | H7: EUR | I7: 37176.16 | J7: GBP | K7: 31677.81 | L7: 1900000661 | M7: 10004 | N7: Not Matched | P7: 90050559
A8: 1800000007 | B8: 20004 | C8: DR | D8: 45624 | E8: 45684 | F8: 90050561 | G8: EU_200 | H8: EUR | I8: 44879.86 | J8: GBP | K8: 38242.13 | L8: 1900000662 | M8: 10004 | N8: Not Matched | P8: 90050561
A9: 1800000008 | B9: 20004 | C9: DR | D9: 45632 | E9: 45692 | F9: 0F00000383 | G9: EU_200 | H9: EUR | I9: 73192.67 | J9: GBP | K9: 62367.47 | L9: 1900000663 | M9: 10004 | N9: Not Matched | P9: 0F00000383
A10: 1800000009 | B10: 20004 | C10: DR | D10: 45632 | E10: 45692 | F10: 0F00000400 | G10: EU_200 | H10: EUR | I10: 118273.38 | J10: GBP | K10: 100780.75 | L10: 1900000664 | M10: 10004 | N10: Not Matched | P10: 0F00000400
A11: 1800000010 | B11: 20004 | C11: DR | D11: 45632 | E11: 45692 | F11: 0F00000406 | G11: EU_200 | H11: EUR | I11: 43374.03 | J11: GBP | K11: 36959.01 | L11: 1900000665 | M11: 10004 | N11: Not Matched | P11: 0F00000406
A12: 1800000011 | B12: 20004 | C12: DR | D12: 45635 | E12: 45695 | F12: 0F00000466 | G12: EU_200 | H12: EUR | I12: 184379.74 | J12: GBP | K12: 157109.98 | L12: 1900000666 | M12: 10004 | N12: Not Matched | P12: 0F00000466
A13: 1800000012 | B13: 20004 | C13: DR | D13: 45635 | E13: 45695 | F13: 0F00000472 | G13: EU_200 | H13: EUR | I13: 11923.77 | J13: GBP | K13: 10160.24 | L13: 1900000667 | M13: 10004 | N13: Not Matched | P13: 0F00000472

Sheet FBL1N AP Mirror
A1: LTM | FBL1N AP MIRROR ITEMS | ERP Document Display
A3: Source AP Document | B3: Vendor Account | C3: Document Type | D3: Document Date | E3: Due Date | F3: Reference | G3: Trading Partner | H3: Document Currency | I3: AP Doc Amount | J3: Local Currency | K3: AP Local Amount | L3: Generated AR Document | M3: Bank Name | N3: Posting Status
A4: 1900000002 | B4: 10004 | C4: KR | D4: 46202 | E4: 46262 | F4: WBS TEST -LAB | G4: EU_200 | H4: EUR | I4: -39000 | J4: GBP | K4: -34054.8 | L4: 1800000003 | M4: DBS Global | N4: Posted
A5: 1900000003 | B5: 10004 | C5: KR | D5: 46202 | E5: 46262 | F5: LAB - NO WBS | G5: EU_200 | H5: EUR | I5: -39000 | J5: GBP | K5: -34054.8 | L5: 1800000004 | M5: DBS Global | N5: Posted
A6: 1900000660 | B6: 10004 | C6: KR | D6: 45624 | E6: 45684 | F6: 90050558 | G6: EU_200 | H6: EUR | I6: -68739.02 | J6: GBP | K6: -58572.52 | L6: 1800000005 | M6: DBS Global | N6: Posted
A7: 1900000661 | B7: 10004 | C7: KR | D7: 45624 | E7: 45684 | F7: 90050559 | G7: EU_200 | H7: EUR | I7: -37176.16 | J7: GBP | K7: -31677.81 | L7: 1800000006 | M7: DBS Global | N7: Posted
A8: 1900000662 | B8: 10004 | C8: KR | D8: 45624 | E8: 45684 | F8: 90050561 | G8: EU_200 | H8: EUR | I8: -44879.86 | J8: GBP | K8: -38242.13 | L8: 1800000007 | M8: DBS Global | N8: Posted
A9: 1900000663 | B9: 10004 | C9: KR | D9: 45632 | E9: 45692 | F9: 0F00000383 | G9: EU_200 | H9: EUR | I9: -73192.67 | J9: GBP | K9: -62367.47 | L9: 1800000008 | M9: DBS Global | N9: Posted
A10: 1900000664 | B10: 10004 | C10: KR | D10: 45632 | E10: 45692 | F10: 0F00000400 | G10: EU_200 | H10: EUR | I10: -118273.38 | J10: GBP | K10: -100780.75 | L10: 1800000009 | M10: DBS Global | N10: Posted
A11: 1900000665 | B11: 10004 | C11: KR | D11: 45632 | E11: 45692 | F11: 0F00000406 | G11: EU_200 | H11: EUR | I11: -43374.03 | J11: GBP | K11: -36959.01 | L11: 1800000010 | M11: DBS Global | N11: Posted
A12: 1900000666 | B12: 10004 | C12: KR | D12: 45635 | E12: 45695 | F12: 0F00000466 | G12: EU_200 | H12: EUR | I12: -184379.74 | J12: GBP | K12: -157109.98 | L12: 1800000011 | M12: DBS Global | N12: Posted
A13: 1900000667 | B13: 10004 | C13: KR | D13: 45635 | E13: 45695 | F13: 0F00000472 | G13: EU_200 | H13: EUR | I13: -11923.77 | J13: GBP | K13: -10160.24 | L13: 1800000012 | M13: DBS Global | N13: Posted

Sheet Reconciliation
A1: LTM | AP VS AR RECONCILIATION | ERP Document Display
A3: Tolerance | B3: 0.01
A5: LTM Invoice No. | B5: SAP AR Document | C5: Source AP Document | D5: Reference | E5: Currency | F5: AR Doc Amount | G5: AP Doc Amount | H5: Doc Variance | I5: Local Currency | J5: AR Local Amount | K5: AP Local Amount | L5: Local Variance | M5: Bank Name | N5: Payment Status | O5: Statement Match | P5: Clearing Document | Q5: Exception Reason | R5: Exception Owner | S5: Recon Status | T5: Reviewer | U5: Review Date
A6: ='Invoice Register'!A4 -> LTM-IC-2026-0001 | B6: ='Invoice Register'!B4 -> 1800000003 | C6: ='Invoice Register'!C4 -> 1900000002 | D6: ='Invoice Register'!K4 -> WBS TEST -LAB | E6: ='Invoice Register'!M4 -> EUR | F6: ='Invoice Register'!N4 -> 39000 | G6: ='Invoice Register'!O4 -> -39000 | H6: =F6+G6 -> 0 | I6: ='Invoice Register'!P4 -> GBP | J6: ='Invoice Register'!Q4 -> 34054.8 | K6: ='Invoice Register'!R4 -> -34054.8 | L6: =J6+K6 -> 0 | M6: ='Invoice Register'!S4 -> DBS Global | N6: ='Invoice Register'!T4 -> Open | O6: Pending | S6: =IF(AND(ABS(H6)<=$B$3,ABS(L6)<=$B$3,O6="Matched"),"Matched","Open / Exception") -> Open / Exception
A7: ='Invoice Register'!A5 -> LTM-IC-2026-0002 | B7: ='Invoice Register'!B5 -> 1800000004 | C7: ='Invoice Register'!C5 -> 1900000003 | D7: ='Invoice Register'!K5 -> LAB - NO WBS | E7: ='Invoice Register'!M5 -> EUR | F7: ='Invoice Register'!N5 -> 39000 | G7: ='Invoice Register'!O5 -> -39000 | H7: =F7+G7 -> 0 | I7: ='Invoice Register'!P5 -> GBP | J7: ='Invoice Register'!Q5 -> 34054.8 | K7: ='Invoice Register'!R5 -> -34054.8 | L7: =J7+K7 -> 0 | M7: ='Invoice Register'!S5 -> DBS Global | N7: ='Invoice Register'!T5 -> Open | O7: Pending | S7: =IF(AND(ABS(H7)<=$B$3,ABS(L7)<=$B$3,O7="Matched"),"Matched","Open / Exception") -> Open / Exception
A8: ='Invoice Register'!A6 -> LTM-IC-2026-0003 | B8: ='Invoice Register'!B6 -> 1800000005 | C8: ='Invoice Register'!C6 -> 1900000660 | D8: ='Invoice Register'!K6 -> 90050558 | E8: ='Invoice Register'!M6 -> EUR | F8: ='Invoice Register'!N6 -> 68739.02 | G8: ='Invoice Register'!O6 -> -68739.02 | H8: =F8+G8 -> 0 | I8: ='Invoice Register'!P6 -> GBP | J8: ='Invoice Register'!Q6 -> 58572.52 | K8: ='Invoice Register'!R6 -> -58572.52 | L8: =J8+K8 -> 0 | M8: ='Invoice Register'!S6 -> DBS Global | N8: ='Invoice Register'!T6 -> Open | O8: Pending | S8: =IF(AND(ABS(H8)<=$B$3,ABS(L8)<=$B$3,O8="Matched"),"Matched","Open / Exception") -> Open / Exception
A9: ='Invoice Register'!A7 -> LTM-IC-2026-0004 | B9: ='Invoice Register'!B7 -> 1800000006 | C9: ='Invoice Register'!C7 -> 1900000661 | D9: ='Invoice Register'!K7 -> 90050559 | E9: ='Invoice Register'!M7 -> EUR | F9: ='Invoice Register'!N7 -> 37176.16 | G9: ='Invoice Register'!O7 -> -37176.16 | H9: =F9+G9 -> 0 | I9: ='Invoice Register'!P7 -> GBP | J9: ='Invoice Register'!Q7 -> 31677.81 | K9: ='Invoice Register'!R7 -> -31677.81 | L9: =J9+K9 -> 0 | M9: ='Invoice Register'!S7 -> DBS Global | N9: ='Invoice Register'!T7 -> Open | O9: Pending | S9: =IF(AND(ABS(H9)<=$B$3,ABS(L9)<=$B$3,O9="Matched"),"Matched","Open / Exception") -> Open / Exception
A10: ='Invoice Register'!A8 -> LTM-IC-2026-0005 | B10: ='Invoice Register'!B8 -> 1800000007 | C10: ='Invoice Register'!C8 -> 1900000662 | D10: ='Invoice Register'!K8 -> 90050561 | E10: ='Invoice Register'!M8 -> EUR | F10: ='Invoice Register'!N8 -> 44879.86 | G10: ='Invoice Register'!O8 -> -44879.86 | H10: =F10+G10 -> 0 | I10: ='Invoice Register'!P8 -> GBP | J10: ='Invoice Register'!Q8 -> 38242.13 | K10: ='Invoice Register'!R8 -> -38242.13 | L10: =J10+K10 -> 0 | M10: ='Invoice Register'!S8 -> DBS Global | N10: ='Invoice Register'!T8 -> Open | O10: Pending | S10: =IF(AND(ABS(H10)<=$B$3,ABS(L10)<=$B$3,O10="Matched"),"Matched","Open / Exception") -> Open / Exception
A11: ='Invoice Register'!A9 -> LTM-IC-2026-0006 | B11: ='Invoice Register'!B9 -> 1800000008 | C11: ='Invoice Register'!C9 -> 1900000663 | D11: ='Invoice Register'!K9 -> 0F00000383 | E11: ='Invoice Register'!M9 -> EUR | F11: ='Invoice Register'!N9 -> 73192.67 | G11: ='Invoice Register'!O9 -> -73192.67 | H11: =F11+G11 -> 0 | I11: ='Invoice Register'!P9 -> GBP | J11: ='Invoice Register'!Q9 -> 62367.47 | K11: ='Invoice Register'!R9 -> -62367.47 | L11: =J11+K11 -> 0 | M11: ='Invoice Register'!S9 -> DBS Global | N11: ='Invoice Register'!T9 -> Open | O11: Pending | S11: =IF(AND(ABS(H11)<=$B$3,ABS(L11)<=$B$3,O11="Matched"),"Matched","Open / Exception") -> Open / Exception
A12: ='Invoice Register'!A10 -> LTM-IC-2026-0007 | B12: ='Invoice Register'!B10 -> 1800000009 | C12: ='Invoice Register'!C10 -> 1900000664 | D12: ='Invoice Register'!K10 -> 0F00000400 | E12: ='Invoice Register'!M10 -> EUR | F12: ='Invoice Register'!N10 -> 118273.38 | G12: ='Invoice Register'!O10 -> -118273.38 | H12: =F12+G12 -> 0 | I12: ='Invoice Register'!P10 -> GBP | J12: ='Invoice Register'!Q10 -> 100780.75 | K12: ='Invoice Register'!R10 -> -100780.75 | L12: =J12+K12 -> 0 | M12: ='Invoice Register'!S10 -> DBS Global | N12: ='Invoice Register'!T10 -> Open | O12: Pending | S12: =IF(AND(ABS(H12)<=$B$3,ABS(L12)<=$B$3,O12="Matched"),"Matched","Open / Exception") -> Open / Exception
A13: ='Invoice Register'!A11 -> LTM-IC-2026-0008 | B13: ='Invoice Register'!B11 -> 1800000010 | C13: ='Invoice Register'!C11 -> 1900000665 | D13: ='Invoice Register'!K11 -> 0F00000406 | E13: ='Invoice Register'!M11 -> EUR | F13: ='Invoice Register'!N11 -> 43374.03 | G13: ='Invoice Register'!O11 -> -43374.03 | H13: =F13+G13 -> 0 | I13: ='Invoice Register'!P11 -> GBP | J13: ='Invoice Register'!Q11 -> 36959.01 | K13: ='Invoice Register'!R11 -> -36959.01 | L13: =J13+K13 -> 0 | M13: ='Invoice Register'!S11 -> DBS Global | N13: ='Invoice Register'!T11 -> Open | O13: Pending | S13: =IF(AND(ABS(H13)<=$B$3,ABS(L13)<=$B$3,O13="Matched"),"Matched","Open / Exception") -> Open / Exception
A14: ='Invoice Register'!A12 -> LTM-IC-2026-0009 | B14: ='Invoice Register'!B12 -> 1800000011 | C14: ='Invoice Register'!C12 -> 1900000666 | D14: ='Invoice Register'!K12 -> 0F00000466 | E14: ='Invoice Register'!M12 -> EUR | F14: ='Invoice Register'!N12 -> 184379.74 | G14: ='Invoice Register'!O12 -> -184379.74 | H14: =F14+G14 -> 0 | I14: ='Invoice Register'!P12 -> GBP | J14: ='Invoice Register'!Q12 -> 157109.98 | K14: ='Invoice Register'!R12 -> -157109.98 | L14: =J14+K14 -> 0 | M14: ='Invoice Register'!S12 -> DBS Global | N14: ='Invoice Register'!T12 -> Open | O14: Pending | S14: =IF(AND(ABS(H14)<=$B$3,ABS(L14)<=$B$3,O14="Matched"),"Matched","Open / Exception") -> Open / Exception
A15: ='Invoice Register'!A13 -> LTM-IC-2026-0010 | B15: ='Invoice Register'!B13 -> 1800000012 | C15: ='Invoice Register'!C13 -> 1900000667 | D15: ='Invoice Register'!K13 -> 0F00000472 | E15: ='Invoice Register'!M13 -> EUR | F15: ='Invoice Register'!N13 -> 11923.77 | G15: ='Invoice Register'!O13 -> -11923.77 | H15: =F15+G15 -> 0 | I15: ='Invoice Register'!P13 -> GBP | J15: ='Invoice Register'!Q13 -> 10160.24 | K15: ='Invoice Register'!R13 -> -10160.24 | L15: =J15+K15 -> 0 | M15: ='Invoice Register'!S13 -> DBS Global | N15: ='Invoice Register'!T13 -> Open | O15: Pending | S15: =IF(AND(ABS(H15)<=$B$3,ABS(L15)<=$B$3,O15="Matched"),"Matched","Open / Exception") -> Open / Exception

Sheet Accounting Entries
A1: LTM | AR AND AP ACCOUNTING ENTRIES | ERP Document Display
A3: LTM Invoice No. | B3: Book | C3: Entity | D3: Document No. | E3: GL Account | F3: Account Description | G3: Debit | H3: Credit | I3: Currency | J3: Reference | K3: Bank Name | L3: Posting Status | M3: Classification
A4: LTM-IC-2026-0001 | B4: AR | C4: LTM Services UK Limited | D4: 1800000003 | E4: 12100000 | F4: Intercompany Trade Receivable | G4: 39000 | H4: 0 | I4: EUR | J4: WBS TEST -LAB | K4: DBS Global | L4: Posted | M4: IC Trade
A5: LTM-IC-2026-0001 | B5: AR | C5: LTM Services UK Limited | D5: 1800000003 | E5: 41010000 | F5: Intercompany Trade Revenue | G5: 0 | H5: 39000 | I5: EUR | J5: WBS TEST -LAB | K5: DBS Global | L5: Posted | M5: IC Trade
A6: LTM-IC-2026-0001 | B6: AP | C6: LTM Solutions Europe GmbH | D6: 1900000002 | E6: 51010000 | F6: Intercompany Trade Expense | G6: 39000 | H6: 0 | I6: EUR | J6: WBS TEST -LAB | K6: DBS Global | L6: Posted | M6: IC Trade
A7: LTM-IC-2026-0001 | B7: AP | C7: LTM Solutions Europe GmbH | D7: 1900000002 | E7: 21300000 | F7: Intercompany Trade Payable | G7: 0 | H7: 39000 | I7: EUR | J7: WBS TEST -LAB | K7: DBS Global | L7: Posted | M7: IC Trade
A8: LTM-IC-2026-0002 | B8: AR | C8: LTM Services UK Limited | D8: 1800000004 | E8: 12100000 | F8: Intercompany Trade Receivable | G8: 39000 | H8: 0 | I8: EUR | J8: LAB - NO WBS | K8: DBS Global | L8: Posted | M8: IC Trade
A9: LTM-IC-2026-0002 | B9: AR | C9: LTM Services UK Limited | D9: 1800000004 | E9: 41010000 | F9: Intercompany Trade Revenue | G9: 0 | H9: 39000 | I9: EUR | J9: LAB - NO WBS | K9: DBS Global | L9: Posted | M9: IC Trade
A10: LTM-IC-2026-0002 | B10: AP | C10: LTM Solutions Europe GmbH | D10: 1900000003 | E10: 51010000 | F10: Intercompany Trade Expense | G10: 39000 | H10: 0 | I10: EUR | J10: LAB - NO WBS | K10: DBS Global | L10: Posted | M10: IC Trade
A11: LTM-IC-2026-0002 | B11: AP | C11: LTM Solutions Europe GmbH | D11: 1900000003 | E11: 21300000 | F11: Intercompany Trade Payable | G11: 0 | H11: 39000 | I11: EUR | J11: LAB - NO WBS | K11: DBS Global | L11: Posted | M11: IC Trade
A12: LTM-IC-2026-0003 | B12: AR | C12: LTM Services UK Limited | D12: 1800000005 | E12: 12100000 | F12: Intercompany Trade Receivable | G12: 68739.02 | H12: 0 | I12: EUR | J12: 90050558 | K12: DBS Global | L12: Posted | M12: IC Trade
A13: LTM-IC-2026-0003 | B13: AR | C13: LTM Services UK Limited | D13: 1800000005 | E13: 41010000 | F13: Intercompany Trade Revenue | G13: 0 | H13: 68739.02 | I13: EUR | J13: 90050558 | K13: DBS Global | L13: Posted | M13: IC Trade
A14: LTM-IC-2026-0003 | B14: AP | C14: LTM Solutions Europe GmbH | D14: 1900000660 | E14: 51010000 | F14: Intercompany Trade Expense | G14: 68739.02 | H14: 0 | I14: EUR | J14: 90050558 | K14: DBS Global | L14: Posted | M14: IC Trade
A15: LTM-IC-2026-0003 | B15: AP | C15: LTM Solutions Europe GmbH | D15: 1900000660 | E15: 21300000 | F15: Intercompany Trade Payable | G15: 0 | H15: 68739.02 | I15: EUR | J15: 90050558 | K15: DBS Global | L15: Posted | M15: IC Trade
... A43: LTM-IC-2026-0010 | B43: AP | C43: LTM Solutions Europe GmbH | D43: 1900000667 | E43: 21300000 | F43: Intercompany Trade Payable | G43: 0 | H43: 11923.77 | I43: EUR | J43: 0F00000472 | K43: DBS Global | L43: Posted | M43: IC Trade
